cloudvirt/__init__.py
cloudvirt/cli.py
cloudvirt/cloudinit.py
cloudvirt/config.py
cloudvirt/driver.py
cloudvirt/log.py
cloudvirt/mkuser.py
cloudvirt/spec.py
cloudvirt/util.py
cloudvirt-0.1.4.dist-info/entry_points.txt
cloudvirt-0.1.4.dist-info/licenses/LICENSE
cloudvirt-0.1.4.dist-info/WHEEL
cloudvirt-0.1.4.dist-info/METADATA
cloudvirt-0.1.4.dist-info/RECORD
