Metadata-Version: 2.4
Name: cloudvirt
Version: 0.1.4
Summary: cloudvirt
Author-email: gottaeat <mss@tutanota.de>
Classifier: License :: OSI Approved :: GNU General Public License v3 or later (GPLv3+)
License-File: LICENSE
Requires-Dist: pycdlib >= 1.14.0
Requires-Dist: PyYAML >= 6.0.0
Requires-Dist: passlib >= 1.6.0
Requires-Dist: libvirt-python >= 9.5.0
Project-URL: Home, https://github.com/gottaeat/cloudvirt
